folium_vectorgrid_geojson/__init__.py
folium_vectorgrid_geojson/heat_map.py
folium_vectorgrid_geojson/template/leaflet_heat.min.js
folium_vectorgrid_geojson/vectorgrid.py
folium_vectorgrid_geojson/vectorgrid_geojson.py
folium_vectorgrid_geojson-1.1.1.dist-info/LICENSE
folium_vectorgrid_geojson-1.1.1.dist-info/METADATA
folium_vectorgrid_geojson-1.1.1.dist-info/WHEEL
folium_vectorgrid_geojson-1.1.1.dist-info/RECORD
