Metadata-Version: 2.1
Name: folium-vectorgrid-geojson
Version: 1.1.1
Summary: VectorGrid plugin for folium
Home-page: https://github.com/zarandras/folium-vectorgrid
License: MIT
Author: Lukács Gábor
Author-email: lukacs.hod@gmail.com
Requires-Python: >=3.9,<4.0
Classifier: License :: OSI Approved :: MIT License
Classifier: Programming Language :: Python :: 3
Classifier: Programming Language :: Python :: 3.9
Classifier: Programming Language :: Python :: 3.10
Classifier: Programming Language :: Python :: 3.11
Requires-Dist: folium (>=0.14.0,<0.15.0)
Project-URL: Repository, https://github.com/zarandras/folium-vectorgrid
